brief_survey/__init__.py
brief_survey/utils.py
brief_survey/core/__init__.py
brief_survey/core/survey.py
brief_survey/core/builders/__init__.py
brief_survey/core/builders/questions.py
brief_survey/core/db/__init__.py
brief_survey/core/db/db_models.py
brief_survey/core/db/repositories/__init__.py
brief_survey/core/db/repositories/base.py
brief_survey/core/exceptions/__init__.py
brief_survey/core/exceptions/questions.py
brief_survey/core/exceptions/validators.py
brief_survey/core/managers/__init__.py
brief_survey/core/managers/complete_survey.py
brief_survey/core/models/__init__.py
brief_survey/core/models/buttons.py
brief_survey/core/models/messages.py
brief_survey/core/models/question.py
brief_survey/core/utils/__init__.py
brief_survey/core/utils/next_question_switcher_decorator.py
brief_survey/validators/__init__.py
brief_survey/validators/date.py
brief_survey/validators/etc.py
brief_survey/validators/person.py
brief_survey-0.2.10.2.dist-info/licenses/LICENSE
brief_survey-0.2.10.2.dist-info/METADATA
brief_survey-0.2.10.2.dist-info/WHEEL
brief_survey-0.2.10.2.dist-info/top_level.txt
brief_survey-0.2.10.2.dist-info/RECORD
