Metadata-Version: 2.4
Name: brief_survey
Version: 0.2.10.2
Summary: Dynamic survey/dialog for aiogram3  with aiogram_dialog and Pydantic support
Home-page: https://github.com/Fugguri/brief_survey
Author: Fugguri
Project-URL: pypi, https://pypi.org/project/brief-survey/
Project-URL: github, https://github.com/Fugguri/brief_survey
Keywords: aiogram3,aiogram,aiogram_dialog,brief
Classifier: Programming Language :: Python :: 3.12
Classifier: License :: OSI Approved :: MIT License
Classifier: Operating System :: OS Independent
Requires-Python: >=3.12
License-File: LICENSE
Requires-Dist: aiogram>=3.20
Requires-Dist: aiogram_dialog>=2.3.1
Requires-Dist: phonenumbers>=9.0.10
Requires-Dist: pydantic>=2.11.7
Requires-Dist: humanfriendly>=10.0
Dynamic: author
Dynamic: classifier
Dynamic: description
Dynamic: description-content-type
Dynamic: home-page
Dynamic: keywords
Dynamic: license-file
Dynamic: project-url
Dynamic: requires-dist
Dynamic: requires-python
Dynamic: summary
